icekube/__init__.py
icekube/attack_paths.py
icekube/cli.py
icekube/config.py
icekube/icekube.py
icekube/kube.py
icekube/log_config.py
icekube/models/__init__.py
icekube/models/_helpers.py
icekube/models/api_resource.py
icekube/models/base.py
icekube/models/cluster.py
icekube/models/clusterrole.py
icekube/models/clusterrolebinding.py
icekube/models/group.py
icekube/models/node.py
icekube/models/pod.py
icekube/models/policyrule.py
icekube/models/role.py
icekube/models/rolebinding.py
icekube/models/secret.py
icekube/models/securitycontextconstraints.py
icekube/models/serviceaccount.py
icekube/models/signer.py
icekube/models/user.py
icekube/neo4j.py
icekube/relationships.py
icekube/utils.py
icekube-1.0.5.dist-info/LICENSE.md
icekube-1.0.5.dist-info/METADATA
icekube-1.0.5.dist-info/WHEEL
icekube-1.0.5.dist-info/entry_points.txt
icekube-1.0.5.dist-info/RECORD
