Metadata-Version: 2.1
Name: icekube
Version: 1.0.5
Summary: 
Author: Mohit Gupta
Author-email: mohit.gupta@withsecure.com
Requires-Python: >=3.8,<4.0
Classifier: Programming Language :: Python :: 3
Classifier: Programming Language :: Python :: 3.8
Classifier: Programming Language :: Python :: 3.9
Classifier: Programming Language :: Python :: 3.10
Classifier: Programming Language :: Python :: 3.11
Classifier: Programming Language :: Python :: 3.12
Requires-Dist: kubernetes (>=28.1,<29.0)
Requires-Dist: neo4j (>=4.0,<5.0)
Requires-Dist: pydantic (>=2.4.2,<3.0.0)
Requires-Dist: tqdm (>=4.66.1,<5.0.0)
Requires-Dist: typer (>=0.9,<0.10)
